<?xml version='1.0' encoding='UTF-8'?>
<!DOCTYPE QuickLink PUBLIC "sailpoint.dtd" "sailpoint.dtd">
<QuickLink action="workflow" category="Manage" created="" id="" messageKey="Password Reset" name="Password Reset">
  <Attributes>
    <Map>
      <entry key="logedInUser">
        <value>
          <Script>
            <Source>
        return currentUser.getName();
        </Source>
          </Script>
        </value>
      </entry>
      <entry key="workflowName" value="Workflow-PasswordReset"/>
      <entry key="workflowSuccess" value="Workflow Launched Successfully"/>
    </Map>
  </Attributes>
  <QuickLinkOptions allowSelf="true" created="" id="">
    <DynamicScopeRef>
      <Reference class="sailpoint.object.DynamicScope" id="" name="Everyone"/>
    </DynamicScopeRef>
  </QuickLinkOptions>
</QuickLink>
